agixtsdk/__init__.py
agixtsdk-0.0.82.dist-info/licenses/LICENSE
tests/__init__.py
tests/test_sdk.py
agixtsdk-0.0.82.dist-info/METADATA
agixtsdk-0.0.82.dist-info/WHEEL
agixtsdk-0.0.82.dist-info/top_level.txt
agixtsdk-0.0.82.dist-info/RECORD
