Metadata-Version: 2.4
Name: agixtsdk
Version: 0.0.82
Summary: The AGiXT SDK for Python.
Author: Josh XT
Author-email: josh@devxt.com
Requires-Python: >=3.10
License-File: LICENSE
Requires-Dist: requests
Requires-Dist: openai
Requires-Dist: pydub
Requires-Dist: tiktoken
Requires-Dist: pydantic
Requires-Dist: pyotp
Dynamic: author
Dynamic: author-email
Dynamic: description
Dynamic: description-content-type
Dynamic: license-file
Dynamic: requires-dist
Dynamic: requires-python
Dynamic: summary
